<?xml version="1.0" encoding="UTF-8"?>
<projectConfig id="vicav_config_vicav">
	<title>VICAV - Vienna Corpus of Arabic Varieties</title>
	<menu>
    <main>
      <dropdown xml:id="dropdown00" title="Project">
        <item xml:id="liVicavMission">Mission</item>
        <item xml:id="liVicavNews">News</item>
        <separator/>
        <item xml:id="liVicavTypesOfText">Types of Text/Data</item>
        <item xml:id="liVicavContributors">Contributors</item>    
        <item xml:id="liVicavLinguistics">Linguistics</item>    
      </dropdown>
      <dropdown xml:id="dropdown01" title="Bibliographies">
        <item xml:id="liBibliographyExplanation">Explanation</item>
        <separator/>
        <item xml:id="navBiblGeoMarkers">All Bibl. Locations</item>
        <item xml:id="navBiblRegMarkers">All Bibl. Regions</item>
        <separator/>
        <item xml:id="navDictGeoRegMarkers">All Dictionaries (Locations + Regions)</item>
        <item xml:id="navTextbookGeoRegMarkers">All Textbooks (Locations + Regions)</item>
        <separator/>
        <item xml:id="liBiblNewQuery">Query Bibliography</item>
        <separator/>
        <item xml:id="liVicavContributeBibliography">Contribute to the Bibliography</item>
      </dropdown>
      <dropdown xml:id="dropdown02" title="Profiles">
        <item xml:id="liProfilesExplanation">Explanation + List</item>
        <separator/>
        <item xml:id="navProfilesGeoRegMarkers">Show All Locations</item>
        <separator/>
        <item xml:id="liVicavContributeProfile">Contribute a Profile</item>
      </dropdown>
      <dropdown xml:id="dropdown03" title="Feature Lists">
        <item xml:id="liFeaturesExplanation">Explanation</item>
        <item xml:id="liVicavCrossFeatureQuery">Cross-examine the VICAV Feature Lists</item>
        <separator></separator>
        <item xml:id="navFeaturesGeoRegMarkers">Show All Locations</item>
        <separator></separator>
        <item xml:id="liVicavContributeFeature">Contribute a Feature List</item>
      </dropdown>
      <dropdown xml:id="dropdown04" title="Samples">
        <item xml:id="liSamplesExplanation">Explanation</item>
        <separator></separator>
        <item xml:id="navSamplesGeoRegMarkers">Show All Locations</item>
        <item xml:id="liExploreSamples">Compare Locations</item>
        <separator></separator>
        <item xml:id="liVicavContributeSampleText">Contribute a Sample Text</item>        
      </dropdown>
      <dropdown xml:id="dropdown05" title="Texts">
        <item xml:id="liCorpusTextsExplanation">Explanation and Overview</item>
      </dropdown>
      <dropdown xml:id="dropdown06" title="Dictionaries">
        <item xml:id="navDictGeoRegMarkers1">Bibliography (Dictionaries)</item>
        <separator/>
        <item xml:id="navVicavDictMarkers">Show All VICAV Dictionaries</item>
        <separator/>
        <item xml:id="liVicavCrossDictQuery">Query the VICAV Dictionaries</item>
        <separator/>
        <item xml:id="liVicavDict_Tunis">TUNICO Dictionary</item>
        <item xml:id="liVicavDict_Damascus">Damascus Dictionary</item>
        <item xml:id="liVicavDict_Cairo">Cairo Dictionary</item>
        <item xml:id="liVicavDict_Baghdad">Baghdad Dictionary</item>
        <item xml:id="liVicavDict_MSA">MSA Dictionary</item>
        <separator/>
        <item xml:id="liVicavDictionariesTechnicalities">Technicalities</item>
        <item xml:id="liVicavContributeDictionary">Contribute a Dictionary/Glossary</item>
      </dropdown>
      <dropdown xml:id="dropdown07" title="Tools &amp; Technology">
        <item xml:id="liVicavDictionaryEncoding">Dictionary Encoding</item>
        <item xml:id="liVicavVLE">Dictionary Editor (VLE)</item>
        <item xml:id="liVicavArabicTools">Arabic Research Tools</item>
        <item xml:id="liVicavOverview_corpora_spoken"><![CDATA[&nbsp;&nbsp;&nbsp;&nbsp;&nbsp;Corpora (Spoken Varieties)]]></item>
        <item xml:id="liVicavOverview_corpora_msa"><![CDATA[&nbsp;&nbsp;&nbsp;&nbsp;&nbsp;Corpora (MSA)]]></item>
        <item xml:id="liVicavOverview_special_corpora"><![CDATA[&nbsp;&nbsp;&nbsp;&nbsp;&nbsp;Special Corpora]]></item>
        <item xml:id="liVicavOverview_corpora_historical_varieties"><![CDATA[&nbsp;&nbsp;&nbsp;&nbsp;&nbsp;Corpora (Historical Varieties)]]></item>
        <item xml:id="liVicavOverview_dictionaries"><![CDATA[&nbsp;&nbsp;&nbsp;&nbsp;&nbsp;Dictionaries]]></item>
        <item xml:id="liVicavOverview_nlp"><![CDATA[&nbsp;&nbsp;&nbsp;&nbsp;&nbsp;Language Processing Tools]]></item>
        <item xml:id="liVicavOverview_otherStuff"><![CDATA[&nbsp;&nbsp;&nbsp;&nbsp;&nbsp;Other Websites &amp; Projects]]></item>                                
        <item xml:id="liVicavLearning">Learning Materials</item>
        <item xml:id="liVicavLearningTextbookDamascus"><![CDATA[&nbsp;&nbsp;&nbsp;&nbsp;&nbsp;Materials for Textbook of Syrian Arabic]]></item>
        <item xml:id="liVicavLearningSmartphone"><![CDATA[&nbsp;&nbsp;&nbsp;&nbsp;&nbsp;Vocabularies on Smartphones]]></item>
        <item xml:id="liVicavLearningPrograms"><![CDATA[&nbsp;&nbsp;&nbsp;&nbsp;&nbsp;Available Programs]]></item>
        <item xml:id="liVicavLearningData"><![CDATA[&nbsp;&nbsp;&nbsp;&nbsp;&nbsp;Available Data]]></item>
        <item xml:id="liVicavKeyboards">Keyboard Layouts</item>
      </dropdown>
    </main>
    <subnav>
      <item xml:id="subNavBiblGeoMarkers" class="active">Bibl. Locations</item>
      <item xml:id="subNavBiblRegMarkers">Bibl. Regions</item>
      <item xml:id="subNavDictGeoRegMarkers">Bibl. (Dictionaries)</item>
      <item xml:id="subNavTextbookGeoRegMarkers">Bibl. (Textbooks)</item>
      <item xml:id="subNavProfilesGeoRegMarkers">Profiles</item>
      <item xml:id="subNavFeaturesGeoRegMarkers">Features</item>
      <item xml:id="subNavSamplesGeoRegMarkers">Samples</item>
      <item xml:id="subNavVicavDictMarkers">VICAV Dictionaries</item>
    </subnav>
	</menu>
</projectConfig>